{
	"users": [
		{
			"id": 1,
			"name": "Juliet Oma",
			"email": "julie@yahoo.com",
			"number": "08100000000"
		},
		{
			"id": 2,
			"name": "James Williams",
			"email": "jameswilly@gmail.com",
			"number": "08111111111"
		},
		{
			"id": 3,
			"name": "Ahmed Ali",
			"email": "ahmedali012@gmail.com",
			"number": "09022222222"
		},
		{
			"id": 4,
			"name": "Grace Funsho",
			"email": "gracefunsho@gmail.com",
			"number": "09033333333"
		},
		{
			"id": 5,
			"name": "Ahmed Tala",
			"email": "ahmedali0dsad12@gmail.com",
			"number": "09022223322"
		}
	],
	"categories": [
		{
			"id": 1,
			"name": "Apple iPhone",
			"img": "cat-iphone.webp",
			"url": "iphone"
		},
		{
			"id": 2,
			"name": "Apple iPad",
			"img": "cat-ipad.webp",
			"url": "ipad"
		},
		{
			"id": 3,
			"name": "Apple iWatch",
			"img": "cat-iwatch.webp",
			"url": "iwatch"
		},
		{
			"id": 4,
			"name": "Apple MacBook",
			"img": "cat-mac.webp",
			"url": "macbook"
		},
		{
			"id": 5,
			"name": "Apple AirPods",
			"img": "cat-airpods.webp",
			"url": "airpods"
		},
		{
			"id": 6,
			"name": "Аксессуары",
			"img": "cat-access.webp",
			"url": "accessories"
		},
		{
			"id": 7,
			"name": "Гаджеты",
			"img": "cat-gad.webp",
			"url": "gadget"
		}
	],
	"products": [
		{
			"id": 1,
			"categoriesID": 1,
			"article": "100100",
			"name": "Apple iPhone 15",
			"img": "iphone-15.webp",
			"label": "Новинка",
			"oldPrice": 105000,
			"newPrice": 95000
		},
		{
			"id": 2,
			"categoriesID": 1,
			"article": "100101",
			"name": "Apple iPhone 15 Pro",
			"img": "iphone-15.webp",
			"label": "Новинка",
			"oldPrice": 105000,
			"newPrice": 95000
		},
		{
			"id": 3,
			"categoriesID": 1,
			"article": "100102",
			"name": "Apple iPhone 15 Pro Max",
			"img": "iphone-15.webp",
			"label": "Хит",
			"oldPrice": 105000,
			"newPrice": 95000
		},
		{
			"id": 4,
			"categoriesID": 1,
			"article": "100103",
			"name": "Apple iPhone 14",
			"img": "iphone-15.webp",
			"label": "Хит",
			"oldPrice": 105000,
			"newPrice": 95000
		},
		{
			"id": 5,
			"categoriesID": 1,
			"article": "100104",
			"name": "Apple iPhone 14 Pro",
			"img": "iphone-15.webp",
			"label": "Хит",
			"oldPrice": 105000,
			"newPrice": 95000
		},
		{
			"id": 6,
			"categoriesID": 1,
			"article": "100105",
			"name": "Apple iPhone 14 Pro Max",
			"img": "iphone-15.webp",
			"label": "Новинка",
			"oldPrice": 105000,
			"newPrice": 95000
		},
		{
			"id": 7,
			"categoriesID": 2,
			"article": "100100",
			"name": "Apple iPad 11",
			"img": "ipad_pro_11.webp",
			"label": "Хит",
			"oldPrice": 105000,
			"newPrice": 95000
		},
		{
			"id": 8,
			"categoriesID": 2,
			"article": "100101",
			"name": "Apple iPad 10",
			"img": "ipad_pro_11.webp",
			"label": "Хит",
			"oldPrice": 105000,
			"newPrice": 95000
		}
	]
}